setup.py
babel/__init__.py
babel/__main__.py
babel/bin/__init__.py
babel/bin/aliases.py
babel/bin/base.py
babel/bin/http.py
babel/bin/sms.py
babel_cli.egg-info/PKG-INFO
babel_cli.egg-info/SOURCES.txt
babel_cli.egg-info/dependency_links.txt
babel_cli.egg-info/entry_points.txt
babel_cli.egg-info/requires.txt
babel_cli.egg-info/top_level.txt
babel_cli.egg-info/zip-safe