Metadata-Version: 1.0
Name: babel-cli
Version: 0.3.5
Summary: A command line interface for sending anything anywhere.
Home-page: https://github.com/Calder/babel-cli
Author: Calder Coalson
Author-email: caldercoalson@gmail.com
License: LICENSE.txt
Platform: UNKNOWN
